epoch_gpu/__init__.py
epoch_gpu/builder.py
epoch_gpu/cli.py
epoch_gpu/config.py
epoch_gpu/analysis/__init__.py
epoch_gpu/analysis/diagnostics.py
epoch_gpu/io/__init__.py
epoch_gpu/io/sdf_reader.py
epoch_gpu/utils/__init__.py
epoch_gpu/utils/deck.py
epoch_gpu/utils/units.py
epoch_gpu-1.0.0.dist-info/LICENSE
epoch_gpu-1.0.0.dist-info/METADATA
epoch_gpu-1.0.0.dist-info/WHEEL
epoch_gpu-1.0.0.dist-info/entry_points.txt
epoch_gpu-1.0.0.dist-info/top_level.txt
epoch_gpu-1.0.0.dist-info/RECORD
