Metadata-Version: 2.1
Name: epoch-gpu
Version: 1.0.0
Summary: GPU-accelerated Particle-In-Cell code for plasma physics simulations
Author: EPOCH-GPU Development Team
Author-email: "Original EPOCH: Keith Bennett" <k.bennett@warwick.ac.uk>
Maintainer-email: Xingqiang Chen <chenxingqiang@gmail.com>
License: GPL-3.0
Project-URL: Homepage, https://github.com/chenxingqiang/EPOCH-GPU
Project-URL: Documentation, https://github.com/chenxingqiang/EPOCH-GPU#readme
Project-URL: Repository, https://github.com/chenxingqiang/EPOCH-GPU.git
Project-URL: Issues, https://github.com/chenxingqiang/EPOCH-GPU/issues
Project-URL: Changelog, https://github.com/chenxingqiang/EPOCH-GPU/blob/main/CHANGELOG.md
Keywords: plasma,physics,particle-in-cell,pic,gpu,cuda,openacc,simulation,hpc
Classifier: Development Status :: 4 - Beta
Classifier: Environment :: GPU :: NVIDIA CUDA
Classifier: Intended Audience :: Science/Research
Classifier: License :: OSI Approved :: GNU General Public License v3 (GPLv3)
Classifier: Operating System :: POSIX :: Linux
Classifier: Programming Language :: Fortran
Classifier: Programming Language :: Python :: 3
Classifier: Programming Language :: Python :: 3.8
Classifier: Programming Language :: Python :: 3.9
Classifier: Programming Language :: Python :: 3.10
Classifier: Programming Language :: Python :: 3.11
Classifier: Programming Language :: Python :: 3.12
Classifier: Topic :: Scientific/Engineering :: Physics
Requires-Python: >=3.8
License-File: LICENSE
Requires-Dist: numpy>=1.20.0
Requires-Dist: matplotlib>=3.3.0
Provides-Extra: dev
Requires-Dist: pytest>=6.0; extra == "dev"
Requires-Dist: pytest-cov; extra == "dev"
Requires-Dist: black; extra == "dev"
Requires-Dist: isort; extra == "dev"
Requires-Dist: flake8; extra == "dev"
Provides-Extra: docs
Requires-Dist: sphinx; extra == "docs"
Requires-Dist: sphinx-rtd-theme; extra == "docs"
